tabulate/__init__.py
tabulate/version.py
tabulate2/__init__.py
tabulate2/version.py
tabulate2-1.10.2.dist-info/LICENSE
tabulate2-1.10.2.dist-info/METADATA
tabulate2-1.10.2.dist-info/WHEEL
tabulate2-1.10.2.dist-info/entry_points.txt
tabulate2-1.10.2.dist-info/top_level.txt
tabulate2-1.10.2.dist-info/RECORD
