Metadata-Version: 2.1
Name: tabulate2
Version: 1.10.2
Summary: Pretty-print tabular data
Author-email: Sergey Astanin <s.astanin@gmail.com>
License: MIT
Project-URL: Homepage, https://github.com/RaSan147/python-tabulate
Classifier: Development Status :: 4 - Beta
Classifier: License :: OSI Approved :: MIT License
Classifier: Operating System :: OS Independent
Classifier: Programming Language :: Python :: 3
Classifier: Programming Language :: Python :: 3.9
Classifier: Programming Language :: Python :: 3.10
Classifier: Programming Language :: Python :: 3.11
Classifier: Programming Language :: Python :: 3.12
Classifier: Programming Language :: Python :: 3.13
Classifier: Topic :: Software Development :: Libraries
Requires-Python: >=3.9
License-File: LICENSE
Requires-Dist: wcwidth>=0.2.13
Provides-Extra: dev
Requires-Dist: tox; extra == "dev"
Requires-Dist: black; extra == "dev"
Requires-Dist: pre-commit; extra == "dev"
Provides-Extra: test
Requires-Dist: pytest; extra == "test"
Requires-Dist: numpy; extra == "test"
Requires-Dist: pandas; extra == "test"
Requires-Dist: wcwidth; extra == "test"
Provides-Extra: widechars
Requires-Dist: wcwidth; extra == "widechars"
